pydrt/ColeColeDRT.py
pydrt/DRT.py
pydrt/DRTPeak.py
pydrt/DebyeDRT.py
pydrt/GaussDRT.py
pydrt/HavriliakNegamiDRT.py
pydrt/__init__.py
pydrt-1.0.dist-info/licenses/LICENSE
pydrt-1.0.dist-info/METADATA
pydrt-1.0.dist-info/WHEEL
pydrt-1.0.dist-info/top_level.txt
pydrt-1.0.dist-info/RECORD
