Metadata-Version: 2.4
Name: PyDRT
Version: 1.0
Summary: A lightweight library for computing DRTs using physical basis functions.
Author-email: Robert Leonhardt <mail@robertleonhardt.de>
License: MIT License
Project-URL: Homepage, https://github.com/robertleonhardt/PyDRT
Project-URL: Source, https://github.com/robertleonhardt/PyDRT
Project-URL: Issues, https://github.com/robertleonhardt/PyDRT/issues
Requires-Python: >=3.10
License-File: LICENSE
Requires-Dist: numpy>=2.2
Requires-Dist: scipy>=1.15
Dynamic: license-file
